smart_git_agent/__init__.py
smart_git_agent/__main__.py
smart_git_agent/cli.py
smart_git_agent/commit_analyze.py
smart_git_agent/config_manager.py
smart_git_agent/file_utils.py
smart_git_agent/smart_git_agent.py
smart_git_agent-1.1.2.dist-info/licenses/LICENSE
smart_git_agent-1.1.2.dist-info/METADATA
smart_git_agent-1.1.2.dist-info/WHEEL
smart_git_agent-1.1.2.dist-info/entry_points.txt
smart_git_agent-1.1.2.dist-info/top_level.txt
smart_git_agent-1.1.2.dist-info/RECORD
