Metadata-Version: 2.4
Name: smart-git-agent
Version: 1.1.2
Summary: An intelligent Git automation tool that monitors file changes and generates AI-powered commit messages.
Author-email: Sosthene Mounsambote <sosthenemounsambote14@gmail.com>
License-Expression: MIT
Requires-Python: >=3.8
License-File: LICENSE
Requires-Dist: gitpython>=3.1.43
Requires-Dist: watchdog>=5.0.2
Requires-Dist: requests>=2.32.3
Requires-Dist: keyboard
Dynamic: license-file
